streamlit_image_crop/__init__.py
streamlit_image_crop/frontend/.prettierrc
streamlit_image_crop/frontend/build/asset-manifest.json
streamlit_image_crop/frontend/build/bootstrap.min.css
streamlit_image_crop/frontend/build/index.html
streamlit_image_crop/frontend/build/static/css/2.21050121.chunk.css
streamlit_image_crop/frontend/build/static/css/2.21050121.chunk.css.map
streamlit_image_crop/frontend/build/static/js/2.f4b416f8.chunk.js
streamlit_image_crop/frontend/build/static/js/2.f4b416f8.chunk.js.LICENSE.txt
streamlit_image_crop/frontend/build/static/js/2.f4b416f8.chunk.js.map
streamlit_image_crop/frontend/build/static/js/main.e37f1242.chunk.js
streamlit_image_crop/frontend/build/static/js/main.e37f1242.chunk.js.map
streamlit_image_crop/frontend/build/static/js/runtime-main.fbbca315.js
streamlit_image_crop/frontend/build/static/js/runtime-main.fbbca315.js.map
streamlit_image_crop-0.2.0.dist-info/LICENSE
streamlit_image_crop-0.2.0.dist-info/WHEEL
streamlit_image_crop-0.2.0.dist-info/METADATA
streamlit_image_crop-0.2.0.dist-info/RECORD
